blitzmanager/__init__.py
blitzmanager/arguments_parser.py
blitzmanager/cmake.py
blitzmanager/command.py
blitzmanager/dependency_builder.py
blitzmanager/flag_observer.py
blitzmanager/logger.py
blitzmanager/main_manager.py
blitzmanager/path.py
blitzmanager/platform.py
blitzmanager/runner.py
blitzmanager/templates_path_loader.py
blitzmanager/text_file.py
blitzmanager/managers/__init__.py
blitzmanager/managers/download.py
blitzmanager/managers/initializer.py
blitzmanager/managers/manager.py
blitzmanager/managers/supported_managers.py
blitzmanager/managers/vcpkg.py
blitzmanager/scraping/__init__.py
blitzmanager/scraping/cmake_creator.py
blitzmanager/scraping/directory_harvester.py
blitzmanager/scraping/directory_parser.py
blitzmanager/scraping/harvester.py
blitzmanager/scraping/headers_extractor.py
blitzmanager/scraping/headers_replacer.py
blitzmanager/scraping/regex_replacer.py
blitzmanager/template_parser/__init__.py
blitzmanager/template_parser/blitz_parser.py
blitzmanager/template_parser/template_generator.py
blitzmanager-0.0.7.dist-info/AUTHORS
blitzmanager-0.0.7.dist-info/LICENSE
blitzmanager-0.0.7.dist-info/METADATA
blitzmanager-0.0.7.dist-info/WHEEL
blitzmanager-0.0.7.dist-info/top_level.txt
blitzmanager-0.0.7.dist-info/RECORD
