Metadata-Version: 2.1
Name: blitzmanager
Version: 0.0.7
Summary: Simple high level manager that uses package managers for C/C++ dependencies.
Home-page: https://github.com/Hussam-Turjman/blitzmanager
Author: Hussam Turjman
Author-email: hussam.turjman@gmail.com
Classifier: Programming Language :: Python :: 3
Classifier: License :: OSI Approved :: BSD License
Classifier: Operating System :: OS Independent
Requires-Python: >=3.8.10
License-File: LICENSE
License-File: AUTHORS
Requires-Dist: requests >=2.26.0
